jgtutils/FXTransact.py
jgtutils/__init__.py
jgtutils/add_pattern_to_home_settings.py
jgtutils/cli_test_from_jgtenv_fxtransact.py
jgtutils/cli_test_from_jgtenv_it.py
jgtutils/cli_test_from_jgtenv_timeframe.py
jgtutils/cli_test_jgtfxcli_helper.py
jgtutils/cli_test_jgtset_config_update_yaml.py
jgtutils/cli_test_patterns.py
jgtutils/cli_test_pov_not_required.py
jgtutils/cli_test_settings.py
jgtutils/cli_test_settings_demo_real.py
jgtutils/cli_test_timeframes.py
jgtutils/cli_tlid_range.py
jgtutils/colconverthelper.py
jgtutils/coltypehelper.py
jgtutils/iprops.py
jgtutils/jgtcliconstants.py
jgtutils/jgtclihelper.py
jgtutils/jgtclirqdata.py
jgtutils/jgtcommon.py
jgtutils/jgtconstants.py
jgtutils/jgtenv.py
jgtutils/jgterrorcodes.py
jgtutils/jgtfxhelper.py
jgtutils/jgtlogging.py
jgtutils/jgtos.py
jgtutils/jgtpov.py
jgtutils/jgtset.py
jgtutils/jgtwslhelper.py
jgtutils/test_fxtrade.py
jgtutils/test_fxtransact.py
jgtutils/test_jgtcommon_datetiming.py
jgtutils/test_jgtcommon_get_ctx_env.py
jgtutils/test_jgtcommon_read_config.py
jgtutils/test_jgtcommon_read_config_from_sample.py
jgtutils/test_jgtcommon_settings.py
jgtutils/test_jgtfxhelper.py
jgtutils/test_jgtos_fix_path.py
jgtutils/test_market_open_or_closed.py
jgtutils/timeframe_scheduler.py
jgtutils/tst_fxtrade.py
jgtutils-1.0.25.dist-info/LICENSE
jgtutils-1.0.25.dist-info/METADATA
jgtutils-1.0.25.dist-info/WHEEL
jgtutils-1.0.25.dist-info/entry_points.txt
jgtutils-1.0.25.dist-info/top_level.txt
jgtutils-1.0.25.dist-info/RECORD
