Metadata-Version: 2.1
Name: jgtutils
Version: 1.0.25
Summary: A utility package common to other JGT projects.
Home-page: https://github.com/jgwill/jgtutils
Author: Guillaume Isabelle
Author-email: Guillaume Isabelle <jgi@jgwill.com>
License: MIT License
Project-URL: Homepage, https://github.com/jgwill/jgtutils
Project-URL: Bug Tracker, https://github.com/jgwill/jgtutils/issues
Keywords: utilities
Classifier: Development Status :: 3 - Alpha
Classifier: Intended Audience :: Developers
Classifier: License :: OSI Approved :: MIT License
Classifier: Programming Language :: Python :: 3
Classifier: Programming Language :: Python :: 3.6
Classifier: Programming Language :: Python :: 3.7
Classifier: Programming Language :: Python :: 3.8
Classifier: Programming Language :: Python :: 3.9
License-File: LICENSE
Requires-Dist: jgtcore >=0.2.5
Requires-Dist: tlid >=0.1.16
Requires-Dist: python-dotenv
Requires-Dist: ruamel.yaml >=0.18.6
Requires-Dist: numpy >=1.20.3
Requires-Dist: PyYAML >=3.13
Requires-Dist: dateutils
